sqla_model_context/__init__.py
sqla_model_context/context.py
sqla_model_context/exc.py
sqla_model_context/py.typed
sqla_model_context-0.2.2.dist-info/LICENSE
sqla_model_context-0.2.2.dist-info/METADATA
sqla_model_context-0.2.2.dist-info/WHEEL
sqla_model_context-0.2.2.dist-info/top_level.txt
sqla_model_context-0.2.2.dist-info/RECORD
