Metadata-Version: 2.1
Name: sqla-model-context
Version: 0.2.2
Summary: Context manager for default relationship values in SQLAlchemy
Home-page: https://github.com/alexrudy/sqla_model_context
Author: Alex Rudy
Author-email: opensource@alexrudy.net
License: MIT
Platform: UNKNOWN
Classifier: License :: OSI Approved :: MIT License
Classifier: Programming Language :: Python :: 3
Classifier: Programming Language :: Python :: 3 :: Only
Classifier: Programming Language :: Python :: 3.7
Classifier: Programming Language :: Python :: 3.8
Classifier: Programming Language :: Python :: Implementation :: CPython
Classifier: Programming Language :: Python :: Implementation :: PyPy
Requires-Python: >=3.7
Requires-Dist: sqlalchemy
Requires-Dist: werkzeug
